myopenopt/__init__.py
myopenopt/__main__.py
myopenopt-0.0.3.dist-info/WHEEL
myopenopt-0.0.3.dist-info/METADATA
myopenopt-0.0.3.dist-info/RECORD
