Metadata-Version: 2.1
Name: myopenopt
Version: 0.0.3
Summary: `myopenopt` is a package for myopenopt.
Home-page: https://github.com/SaitoTsutomu/myopenopt
Author: Mikio Kubo
Author-email: kubomikio@gmail.com
Requires-Python: >=3.7.0,<3.8.0
Classifier: Development Status :: 1 - Planning
Classifier: License :: OSI Approved :: Python Software Foundation License
Classifier: Programming Language :: Python
Classifier: Programming Language :: Python :: 3
Classifier: Programming Language :: Python :: 3.7
Classifier: Topic :: Scientific/Engineering
Classifier: Topic :: Software Development
Requires-Dist: FuncDesigner (>=0.5629,<0.5630)
Requires-Dist: openopt (>=0.5629,<0.5630)
